workgraph_collections/__init__.py
workgraph_collections/bader.py
workgraph_collections/ase/__init__.py
workgraph_collections/ase/common/__init__.py
workgraph_collections/ase/common/core_level.py
workgraph_collections/ase/common/eos.py
workgraph_collections/ase/emt/__init__.py
workgraph_collections/ase/emt/atomization_energy.py
workgraph_collections/ase/emt/base.py
workgraph_collections/ase/espresso/__init__.py
workgraph_collections/ase/espresso/atomization_energy.py
workgraph_collections/ase/espresso/bader.py
workgraph_collections/ase/espresso/bands.py
workgraph_collections/ase/espresso/base.py
workgraph_collections/ase/espresso/elastic.py
workgraph_collections/ase/espresso/eos.py
workgraph_collections/ase/espresso/oer.py
workgraph_collections/ase/espresso/pdos.py
workgraph_collections/ase/espresso/xas.py
workgraph_collections/ase/espresso/xps.py
workgraph_collections/common/__init__.py
workgraph_collections/common/eos.py
workgraph_collections/common/xps.py
workgraph_collections/cp2k/__init__.py
workgraph_collections/cp2k/eos.py
workgraph_collections/cp2k/xps.py
workgraph_collections/gpaw/base.py
workgraph_collections/gpaw/wannier90.py
workgraph_collections/qe/__init__.py
workgraph_collections/qe/bader.py
workgraph_collections/qe/bands.py
workgraph_collections/qe/eos.py
workgraph_collections/qe/pdos.py
workgraph_collections/qe/relax.py
workgraph_collections/qe/utils.py
workgraph_collections/qe/wannier90_bands.py
workgraph_collections/qe/wannier90_minimal.py
workgraph_collections/qe/wannier90_minimal_base.py
workgraph_collections/qe/xps.py
workgraph_collections-0.1.6.dist-info/LICENSE
workgraph_collections-0.1.6.dist-info/WHEEL
workgraph_collections-0.1.6.dist-info/METADATA
workgraph_collections-0.1.6.dist-info/RECORD
