Metadata-Version: 2.1
Name: workgraph-collections
Version: 0.1.6
Summary: Collections of node-based workflow created using aiida-workgraph.
Keywords: aiida,workflows
Author-email: Xing Wang <xingwang1991@gmail.com>
Requires-Python: >=3.9
Classifier: Development Status :: 1 - Planning
Classifier: Framework :: AiiDA
Classifier: License :: OSI Approved :: MIT License
Classifier: Operating System :: POSIX :: Linux
Classifier: Operating System :: MacOS :: MacOS X
Classifier: Programming Language :: Python
Classifier: Programming Language :: Python :: 3.9
Classifier: Programming Language :: Python :: 3.10
Classifier: Programming Language :: Python :: 3.11
Classifier: Programming Language :: Python :: 3.12
Classifier: Topic :: Scientific/Engineering
Requires-Dist: aiida-workgraph>=0.3.10
Requires-Dist: ase>=3.23.0
Requires-Dist: ase-quantumespresso
Requires-Dist: aiida-quantumespresso
Requires-Dist: aiida-cp2k
Requires-Dist: aiida-bader
Requires-Dist: sphinx_rtd_theme ; extra == "docs"
Requires-Dist: sphinx~=7.2 ; extra == "docs"
Requires-Dist: sphinx-copybutton~=0.5.0 ; extra == "docs"
Requires-Dist: sphinx-design~=0.5.0 ; extra == "docs"
Requires-Dist: sphinx-notfound-page~=1.0 ; extra == "docs"
Requires-Dist: sphinxext-rediraffe~=0.2.4 ; extra == "docs"
Requires-Dist: sphinx-intl~=2.1.0 ; extra == "docs"
Requires-Dist: myst-nb~=1.0.0 ; extra == "docs"
Requires-Dist: nbsphinx ; extra == "docs"
Requires-Dist: pre-commit~=2.2 ; extra == "pre-commit"
Requires-Dist: pylint~=2.17.4 ; extra == "pre-commit"
Requires-Dist: pytest~=7.0 ; extra == "tests"
Requires-Dist: pytest-cov~=2.7,<2.11 ; extra == "tests"
Requires-Dist: playwright ; extra == "tests"
Requires-Dist: httpx ; extra == "tests"
Project-URL: Documentation, https://workgraph-collections.readthedocs.io
Project-URL: Source, https://github.com/superstar54/workgraph-collections
Provides-Extra: docs
Provides-Extra: pre-commit
Provides-Extra: tests
